[
    { "subject": "Science", "question": "प्रकाश संश्लेषण में कौन सी गैस निकलती है?", "options": ["Nitrogen", "Oxygen", "CO2", "Hydrogen"], "answer": "Oxygen" },
    { "subject": "Science", "question": "मानव शरीर की सबसे बड़ी ग्रंथि कौन सी है?", "options": ["Pancreas", "Thyroid", "Liver", "Adrenal"], "answer": "Liver" },
    { "subject": "Science", "question": "विद्युत धारा को मापने वाला यंत्र है?", "options": ["Ammeter", "Voltmeter", "Galvanometer", "Ohmeter"], "answer": "Ammeter" },
    { "subject": "Science", "question": "पीएच (pH) स्केल की सीमा क्या होती है?", "options": ["1-10", "0-14", "1-7", "0-100"], "answer": "0-14" },
    { "subject": "Science", "question": "लोहे पर जंग लगना किस प्रकार की अभिक्रिया है?", "options": ["Redox", "Displacement", "Oxidation", "Reduction"], "answer": "Oxidation" },
    { "subject": "Science", "question": "आनुवंशिकी का जनक किसे कहा जाता है?", "options": ["Newton", "Darwin", "Mendel", "Lamarck"], "answer": "Mendel" },
    { "subject": "Science", "question": "शुद्ध जल का pH मान कितना होता है?", "options": ["6", "7", "8", "9"], "answer": "7" },
    { "subject": "Science", "question": "कोशिका का पावरहाउस किसे कहते हैं?", "options": ["Ribosome", "Nucleus", "Mitochondria", "Golgi Body"], "answer": "Mitochondria" },
    { "subject": "Science", "question": "पोटेशियम का रासायनिक प्रतीक क्या है?", "options": ["P", "Po", "K", "Pt"], "answer": "K" },
    { "subject": "Science", "question": "अवतल दर्पण का उपयोग कहाँ होता है?", "options": ["Side Mirror", "Shaving Mirror", "Rear View", "None"], "answer": "Shaving Mirror" },

    { "subject": "Maths", "question": "सबसे छोटी अभाज्य संख्या (Prime Number) कौन सी है?", "options": ["1", "2", "3", "5"], "answer": "2" },
    { "subject": "Maths", "question": "वृत्त की परिधि (Circumference) का सूत्र क्या है?", "options": ["πr²", "2πr", "πd²", "4πr"], "answer": "2πr" },
    { "subject": "Maths", "question": "sin 90° का मान क्या होता है?", "options": ["0", "1/2", "1", "undefined"], "answer": "1" },
    { "subject": "Maths", "question": "एक समकोण त्रिभुज का एक कोण होता है?", "options": ["45°", "60°", "90°", "180°"], "answer": "90°" },
    { "subject": "Maths", "question": "वर्ग का क्षेत्रफल क्या होता है?", "options": ["side * 4", "side * side", "2 * side", "side³"], "answer": "side * side" },
    { "subject": "Maths", "question": "√144 का मान क्या है?", "options": ["10", "11", "12", "14"], "answer": "12" },
    { "subject": "Maths", "question": "दो संख्याओं का योग 15 है और अंतर 3, संख्याएं क्या हैं?", "options": ["9, 6", "10, 5", "8, 7", "11, 4"], "answer": "9, 6" },
    { "subject": "Maths", "question": "गोले का आयतन (Volume) क्या है?", "options": ["4/3 πr³", "πr²h", "1/3 πr²h", "2/3 πr³"], "answer": "4/3 πr³" },
    { "subject": "Maths", "question": "बहुपद x² - 4 के शून्यक क्या होंगे?", "options": ["2, -2", "4, -4", "0, 4", "2, 0"], "answer": "2, -2" },
    { "subject": "Maths", "question": "π (पाई) कैसी संख्या है?", "options": ["Rational", "Irrational", "Integer", "Natural"], "answer": "Irrational" },

    { "subject": "Social Science", "question": "भारतीय संविधान कब लागू हुआ?", "options": ["1947", "1948", "1950", "1952"], "answer": "1950" },
    { "subject": "Social Science", "question": "हड़प्पा सभ्यता की खोज किसने की थी?", "options": ["Daya Ram Sahni", "RD Banerji", "Wheeler", "Cunningham"], "answer": "Daya Ram Sahni" },
    { "subject": "Social Science", "question": "सौरमंडल का सबसे बड़ा ग्रह कौन सा है?", "options": ["Earth", "Mars", "Jupiter", "Saturn"], "answer": "Jupiter" },
    { "subject": "Social Science", "question": "चाय का सबसे बड़ा उत्पादक देश कौन सा है?", "options": ["India", "China", "Brazil", "Kenya"], "answer": "China" },
    { "subject": "Social Science", "question": "सूचना का अधिकार (RTI) कब पारित हुआ?", "options": ["2003", "2005", "2008", "2010"], "answer": "2005" },
    { "subject": "Social Science", "question": "राज्यसभा का पदेन सभापति कौन होता है?", "options": ["President", "Prime Minister", "Vice President", "Speaker"], "answer": "Vice President" },
    { "subject": "Social Science", "question": "फ्रांसीसी क्रांति कब हुई थी?", "options": ["1776", "1789", "1804", "1815"], "answer": "1789" },
    { "subject": "Social Science", "question": "काली मिट्टी किस फसल के लिए उपयुक्त है?", "options": ["Wheat", "Rice", "Cotton", "Tea"], "answer": "Cotton" },
    { "subject": "Social Science", "question": "नीति आयोग का अध्यक्ष कौन होता है?", "options": ["President", "Finance Minister", "Prime Minister", "RBI Governor"], "answer": "Prime Minister" },
    { "subject": "Social Science", "question": "भाखड़ा नांगल बांध किस नदी पर है?", "options": ["Ganga", "Sutlej", "Yamuna", "Beas"], "answer": "Sutlej" },

    { "subject": "Hindi", "question": "स्वर संधि के कितने भेद होते हैं?", "options": ["3", "4", "5", "6"], "answer": "5" },
    { "subject": "Hindi", "question": "रामचरितमानस के रचयिता कौन हैं?", "options": ["Surdas", "Kabir", "Tulsidas", "Valmiki"], "answer": "Tulsidas" },
    { "subject": "Hindi", "question": "आकाश का पर्यायवाची शब्द है?", "options": ["नीर", "गगन", "पावक", "अनल"], "answer": "गगन" },
    { "subject": "Hindi", "question": "'नाक कटना' मुहावरे का अर्थ क्या है?", "options": ["चोट लगना", "बेइज्जती होना", "झगड़ा होना", "गुस्सा आना"], "answer": "बेइज्जती होना" },
    { "subject": "Hindi", "question": "लंबोदर में कौन सा समास है?", "options": ["Avyayibhav", "Tatpurush", "Bahuvrihi", "Dwigu"], "answer": "Bahuvrihi" },
    { "subject": "Hindi", "question": "संज्ञा के कितने भेद होते हैं?", "options": ["2", "3", "5", "4"], "answer": "5" },
    { "subject": "Hindi", "question": "'उत्थान' का विलोम शब्द क्या है?", "options": ["पतन", "अवनति", "गिरावट", "नीचे"], "answer": "पतन" },
    { "subject": "Hindi", "question": "हिंदी दिवस कब मनाया जाता है?", "options": ["14 Sept", "15 Aug", "26 Jan", "2 Oct"], "answer": "14 Sept" },
    { "subject": "Hindi", "question": "वर्णों के समूह को क्या कहते हैं?", "options": ["शब्द", "वाक्य", "वर्णमाला", "पद"], "answer": "वर्णमाला" },
    { "subject": "Hindi", "question": "शुद्ध शब्द चुनिए:", "options": ["आशिर्वाद", "आशीर्वाद", "असीर्वाद", "अशिरवाद"], "answer": "आशीर्वाद" },

    { "subject": "English", "question": "What is the plural of 'Child'?", "options": ["Childs", "Children", "Childrens", "Childes"], "answer": "Children" },
    { "subject": "English", "question": "Identify the Verb: 'She is running fast.'", "options": ["She", "Fast", "Running", "Is"], "answer": "Running" },
    { "subject": "English", "question": "Antonym of 'Beautiful'?", "options": ["Pretty", "Ugly", "Nice", "Smart"], "answer": "Ugly" },
    { "subject": "English", "question": "Choose the correct Article: 'He is __ honest man.'", "options": ["a", "an", "the", "no article"], "answer": "an" },
    { "subject": "English", "question": "Past tense of 'Go'?", "options": ["Gone", "Went", "Goes", "Going"], "answer": "Went" },
    { "subject": "English", "question": "Synonym of 'Happy'?", "options": ["Sad", "Joyful", "Angry", "Brave"], "answer": "Joyful" },
    { "subject": "English", "question": "Which one is a Vowel?", "options": ["B", "K", "E", "Z"], "answer": "E" },
    { "subject": "English", "question": "Collective noun for 'Birds'?", "options": ["Flock", "Herd", "Pack", "School"], "answer": "Flock" },
    { "subject": "English", "question": "A person who writes books is an __.", "options": ["Actor", "Author", "Artist", "Baker"], "answer": "Author" },
    { "subject": "English", "question": "Opposite of 'Always'?", "options": ["Sometime", "Never", "Everyday", "Daily"], "answer": "Never" },

    { "subject": "Sanskrit/IT", "question": "कम्प्यूटर का जनक किसे कहा जाता है?", "options": ["Bill Gates", "Charles Babbage", "Newton", "Tesla"], "answer": "Charles Babbage" },
    { "subject": "Sanskrit/IT", "question": "पठति' में कौन सा लकार है?", "options": ["लट्", "लृट्", "लङ्", "लोट्"], "answer": "लट्" },
    { "subject": "Sanskrit/IT", "question": "RAM की फुल फॉर्म क्या है?", "options": ["Read Memory", "Random Access Memory", "Ready Memory", "None"], "answer": "Random Access Memory" },
    { "subject": "Sanskrit/IT", "question": "बालकाय' में कौन सी विभक्ति है?", "options": ["प्रथमा", "द्वितीया", "तृतीया", "चतुर्थी"], "answer": "चतुर्थी" },
    { "subject": "Sanskrit/IT", "question": "WWW का आविष्कार किसने किया?", "options": ["Steve Jobs", "Tim Berners-Lee", "Mark Zuckerberg", "Google"], "answer": "Tim Berners-Lee" },
    { "subject": "Sanskrit/IT", "question": "संस्कृत में कितने कारक होते हैं?", "options": ["6", "7", "8", "5"], "answer": "6" },
    { "subject": "Sanskrit/IT", "question": "CPU का मुख्य कार्य क्या है?", "options": ["Storage", "Processing", "Input", "Output"], "answer": "Processing" },
    { "subject": "Sanskrit/IT", "question": "विद्यालय:' का संधि विच्छेद क्या है?", "options": ["विद्य + लय", "विद्या + आलय", "विद्य + आलय", "वि + द्यालय"], "answer": "विद्या + आलय" },
    { "subject": "Sanskrit/IT", "question": "सबसे तेज कम्प्यूटर कौन सा है?", "options": ["Laptop", "Micro", "Super Computer", "Mainframe"], "answer": "Super Computer" },
    { "subject": "Sanskrit/IT", "question": "गच्छति' किस धातु का रूप है?", "options": ["गम्", "गच्छ", "पठ्", "लिख्"], "answer": "गम्" }
    { "subject": "Science", "question": "ध्वनि की चाल सबसे अधिक किसमें होती है?", "options": ["वायु", "जल", "इस्पात (Steel)", "निर्वात"], "answer": "इस्पात (Steel)" },
    { "subject": "Science", "question": "विटामिन C का रासायनिक नाम क्या है?", "options": ["Retinol", "Ascorbic Acid", "Calciferol", "Tocopherol"], "answer": "Ascorbic Acid" },
    { "subject": "Science", "question": "गुरुत्वाकर्षण का नियम किसने दिया?", "options": ["Einstein", "Newton", "Galileo", "Bohr"], "answer": "Newton" },
    { "subject": "Science", "question": "वायुमंडल में सबसे अधिक गैस कौन सी है?", "options": ["Oxygen", "CO2", "Nitrogen", "Argon"], "answer": "Nitrogen" },
    { "subject": "Science", "question": "मानव शरीर का सामान्य तापमान कितना होता है?", "options": ["37°C", "98°C", "42°C", "35°C"], "answer": "37°C" },
    { "subject": "Science", "question": "सोने का रासायनिक प्रतीक क्या है?", "options": ["Ag", "Fe", "Au", "Cu"], "answer": "Au" },
    { "subject": "Science", "question": "कार्य का मात्रक (Unit) क्या है?", "options": ["Watt", "Joule", "Newton", "Volt"], "answer": "Joule" },
    { "subject": "Science", "question": "अम्ल नीले लिटमस को किस रंग में बदल देते हैं?", "options": ["पीला", "हरा", "लाल", "बैंगनी"], "answer": "लाल" },
    { "subject": "Science", "question": "प्रकाश की गति कितनी होती है?", "options": ["3 लाख km/s", "1 लाख km/s", "5 लाख km/s", "2 लाख km/s"], "answer": "3 लाख km/s" },
    { "subject": "Science", "question": "रक्त का थक्का जमने में कौन सा विटामिन सहायक है?", "options": ["Vit A", "Vit B", "Vit E", "Vit K"], "answer": "Vit K" },

    { "subject": "Maths", "question": "त्रिभुज के तीनों कोणों का योग कितना होता है?", "options": ["90°", "180°", "270°", "360°"], "answer": "180°" },
    { "subject": "Maths", "question": "सबसे छोटी पूर्ण संख्या (Whole Number) कौन सी है?", "options": ["1", "0", "-1", "2"], "answer": "0" },
    { "subject": "Maths", "question": "बेलन (Cylinder) के आयतन का सूत्र क्या है?", "options": ["πr²h", "2πrh", "1/3 πr²h", "πrl"], "answer": "πr²h" },
    { "subject": "Maths", "question": "एक वृत्त का व्यास 14cm है, उसकी त्रिज्या क्या होगी?", "options": ["28cm", "14cm", "7cm", "21cm"], "answer": "7cm" },
    { "subject": "Maths", "question": "100 का वर्गमूल (Square Root) क्या है?", "options": ["50", "10", "20", "5"], "answer": "10" },
    { "subject": "Maths", "question": "प्रथम 5 सम संख्याओं का माध्य क्या होगा?", "options": ["4", "5", "6", "10"], "answer": "6" },
    { "subject": "Maths", "question": "sin²θ + cos²θ = ?", "options": ["0", "1", "2", "-1"], "answer": "1" },
    { "subject": "Maths", "question": "आयत का परिमाप (Perimeter) क्या है?", "options": ["L * B", "2(L+B)", "L² + B²", "4L"], "answer": "2(L+B)" },
    { "subject": "Maths", "question": "0.5 को प्रतिशत में बदलें:", "options": ["5%", "50%", "0.5%", "500%"], "answer": "50%" },
    { "subject": "Maths", "question": "सबसे बड़ी दो अंकीय संख्या कौन सी है?", "options": ["90", "99", "100", "89"], "answer": "99" },

    { "subject": "Social Science", "question": "भारत का प्रथम नागरिक कौन होता है?", "options": ["PM", "President", "CJ", "Governor"], "answer": "President" },
    { "subject": "Social Science", "question": "अंध महाद्वीप किसे कहा जाता है?", "options": ["Asia", "Africa", "Europe", "Australia"], "answer": "Africa" },
    { "subject": "Social Science", "question": "जलियाँवाला बाग हत्याकांड कब हुआ?", "options": ["1915", "1919", "1921", "1925"], "answer": "1919" },
    { "subject": "Social Science", "question": "हीराकुंड बांध किस राज्य में स्थित है?", "options": ["Punjab", "Odisha", "Bihar", "Rajasthan"], "answer": "Odisha" },
    { "subject": "Social Science", "question": "लोकसभा का कार्यकाल कितने वर्ष का होता है?", "options": ["4", "5", "6", "2"], "answer": "5" },
    { "subject": "Social Science", "question": "विश्व का सबसे बड़ा संविधान किस देश का है?", "options": ["USA", "UK", "India", "China"], "answer": "India" },
    { "subject": "Social Science", "question": "गुलाबी शहर (Pink City) किसे कहते हैं?", "options": ["Jodhpur", "Udaipur", "Jaipur", "Ajmer"], "answer": "Jaipur" },
    { "subject": "Social Science", "question": "करो या मरो का नारा किसने दिया?", "options": ["Nehru", "Subhash", "Gandhiji", "Bhagat Singh"], "answer": "Gandhiji" },
    { "subject": "Social Science", "question": "पृथ्वी दिवस कब मनाया जाता है?", "options": ["22 April", "5 June", "10 Dec", "15 Aug"], "answer": "22 April" },
    { "subject": "Social Science", "question": "गौतम बुद्ध का जन्म कहाँ हुआ था?", "options": ["Bodhgaya", "Sarnath", "Lumbini", "Kushinagar"], "answer": "Lumbini" },

    { "subject": "Hindi", "question": "अमृत' का विलोम शब्द क्या है?", "options": ["सुधा", "विष", "जल", "मीठा"], "answer": "विष" },
    { "subject": "Hindi", "question": "पंचवटी में कौन सा समास है?", "options": ["Dwigu", "Dwandwa", "Avyayibhav", "Tatpurush"], "answer": "Dwigu" },
    { "subject": "Hindi", "question": "सूर्य का पर्यायवाची शब्द नहीं है?", "options": ["दिनकर", "रवि", "शशि", "भास्कर"], "answer": "शशि" },
    { "subject": "Hindi", "question": "कामयानी' महाकाव्य के रचयिता कौन हैं?", "options": ["Prasad", "Pant", "Nirala", "Mahadevi"], "answer": "Prasad" },
    { "subject": "Hindi", "question": "आँखें दिखाना' मुहावरे का अर्थ है?", "options": ["प्यार करना", "डराना", "देखना", "अंधा होना"], "answer": "डराना" },
    { "subject": "Hindi", "question": "अ' वर्ण का उच्चारण स्थान क्या है?", "options": ["कण्ठ", "तालु", "मूर्धा", "दन्त"], "answer": "कण्ठ" },
    { "subject": "Hindi", "question": "जो कम बोलता हो, उसे क्या कहते हैं?", "options": ["वाचाल", "मितभाषी", "मूक", "अल्पभाषी"], "answer": "मितभाषी" },
    { "subject": "Hindi", "question": "पवन' का संधि विच्छेद क्या है?", "options": ["प + वन", "पौ + अन", "पो + अन", "पव + न"], "answer": "पो + अन" },
    { "subject": "Hindi", "question": "शुद्ध वर्तनी वाला शब्द है:", "options": ["कवियत्री", "कवयित्री", "कविइत्री", "कवियतत्री"], "answer": "कवयित्री" },
    { "subject": "Hindi", "question": "दाल में काला होना' का अर्थ है?", "options": ["शक होना", "नुकसान होना", "दाल जलना", "खाना खराब होना"], "answer": "शक होना" },

    { "subject": "English", "question": "Synonym of 'Large'?", "options": ["Small", "Huge", "Thin", "Short"], "answer": "Huge" },
    { "subject": "English", "question": "The sun ___ in the east.", "options": ["rise", "rises", "rising", "rose"], "answer": "rises" },
    { "subject": "English", "question": "Definition of an Adjective?", "options": ["Action word", "Naming word", "Describing word", "Connecting word"], "answer": "Describing word" },
    { "subject": "English", "question": "Opposite of 'Rich'?", "options": ["Poor", "Wealthy", "Kind", "Happy"], "answer": "Poor" },
    { "subject": "English", "question": "Which one is a Pronoun?", "options": ["Ram", "He", "City", "Apple"], "answer": "He" },
    { "subject": "English", "question": "What is the feminine of 'King'?", "options": ["Princess", "Queen", "Lady", "Girl"], "answer": "Queen" },
    { "subject": "English", "question": "Choose correctly: 'I ___ a student.'", "options": ["is", "am", "are", "be"], "answer": "am" },
    { "subject": "English", "question": "How many letters are in English Alphabet?", "options": ["24", "25", "26", "21"], "answer": "26" },
    { "subject": "English", "question": "Which is a 'Silent letter' in 'Knee'?", "options": ["K", "N", "E", "None"], "answer": "K" },
    { "subject": "English", "question": "Plural of 'Mouse'?", "options": ["Mouses", "Mice", "Mices", "Mousen"], "answer": "Mice" },

    { "subject": "Sanskrit/IT", "question": "कम्प्यूटर की याददाश्त (Memory) किसे कहते हैं?", "options": ["CPU", "RAM", "Mouse", "Keyboard"], "answer": "RAM" },
    { "subject": "Sanskrit/IT", "question": "बालक:' में कौन सा वचन है?", "options": ["एकवचन", "द्विवचन", "बहुवचन", "कोई नहीं"], "answer": "एकवचन" },
    { "subject": "Sanskrit/IT", "question": "Email का फुल फॉर्म क्या है?", "options": ["Electric Mail", "Electronic Mail", "Easy Mail", "Extra Mail"], "answer": "Electronic Mail" },
    { "subject": "Sanskrit/IT", "question": "पटिष्यति' में कौन सा लकार है?", "options": ["लट्", "लृट्", "लङ्", "लोट्"], "answer": "लृट्" },
    { "subject": "Sanskrit/IT", "question": "1 KB में कितने Bytes होते हैं?", "options": ["1000", "1024", "2048", "512"], "answer": "1024" },
    { "subject": "Sanskrit/IT", "question": "संस्कृत में कितने पुरुष होते हैं?", "options": ["2", "3", "4", "5"], "answer": "3" },
    { "subject": "Sanskrit/IT", "question": "HTTP की फुल फॉर्म क्या है?", "options": ["Hyper Text Transfer Protocol", "Hyper Test Text Port", "High Tech Transfer Path", "None"], "answer": "Hyper Text Transfer Protocol" },
    { "subject": "Sanskrit/IT", "question": "अशुद्ध पद चुनें:", "options": ["गच्छति", "लिखति", "पठन्ति", "गच्छसि"], "answer": "पठन्ति" },
    { "subject": "Sanskrit/IT", "question": "कम्प्यूटर का दिमाग किसे कहा जाता है?", "options": ["Monitor", "UPS", "CPU", "Hard Disk"], "answer": "CPU" },
    { "subject": "Sanskrit/IT", "question": "सः गृहम् ___ । (वह घर जाता है)", "options": ["गच्छति", "गच्छामि", "गच्छसि", "गच्छन्ति"], "answer": "गच्छति" }
]
